assemblyish/__init__.py
assemblyish/compiler.py
assemblyish/errors.py
assemblyish/instruction.py
assemblyish/parser.py
assemblyish-1.1.0.dist-info/LICENSE
assemblyish-1.1.0.dist-info/WHEEL
assemblyish-1.1.0.dist-info/METADATA
assemblyish-1.1.0.dist-info/RECORD
